taika/__init__.py
taika/cli.py
taika/events.py
taika/ext/__init__.py
taika/ext/collections.py
taika/ext/excerpt.py
taika/ext/layouts.py
taika/ext/rst.py
taika/frontmatter.py
taika/taika.py
taika/utils.py
taika-0.6.0.dist-info/entry_points.txt
taika-0.6.0.dist-info/LICENSE
taika-0.6.0.dist-info/WHEEL
taika-0.6.0.dist-info/METADATA
taika-0.6.0.dist-info/RECORD
