Metadata-Version: 2.1
Name: taika
Version: 0.6.0
Summary: Another Static Site Generator
Home-page: https://gitlab.com/hectormartinez/taika
License: MIT
Keywords: static site generator
Author: Hector Martinez
Author-email: hector.martinez.ub@gmail.com
Requires-Python: >=3.6,<4.0
Classifier: Development Status :: 2 - Pre-Alpha
Classifier: Intended Audience :: Developers
Classifier: License :: OSI Approved :: MIT License
Classifier: Natural Language :: English
Classifier: Programming Language :: Python :: 3
Classifier: Programming Language :: Python :: 3.6
Classifier: Programming Language :: Python :: 3.7
Requires-Dist: beautifulsoup4
Requires-Dist: docutils
Requires-Dist: jinja2
Requires-Dist: ruamel.yaml
Project-URL: Documentation, https://taika.readthedocs.io/en/latest/
Project-URL: Repository, https://gitlab.com/hectormartinez/taika
